odoo8_addon_account_voucher_killer-8.0.1.0.0.99.dev6-py2.7-nspkg.pth
odoo8_addon_account_voucher_killer-8.0.1.0.0.99.dev6.dist-info/DESCRIPTION.rst
odoo8_addon_account_voucher_killer-8.0.1.0.0.99.dev6.dist-info/METADATA
odoo8_addon_account_voucher_killer-8.0.1.0.0.99.dev6.dist-info/RECORD
odoo8_addon_account_voucher_killer-8.0.1.0.0.99.dev6.dist-info/WHEEL
odoo8_addon_account_voucher_killer-8.0.1.0.0.99.dev6.dist-info/metadata.json
odoo8_addon_account_voucher_killer-8.0.1.0.0.99.dev6.dist-info/namespace_packages.txt
odoo8_addon_account_voucher_killer-8.0.1.0.0.99.dev6.dist-info/top_level.txt
odoo_addons/account_voucher_killer/README.rst
odoo_addons/account_voucher_killer/__init__.py
odoo_addons/account_voucher_killer/__openerp__.py
odoo_addons/account_voucher_killer/invoice_data.xml
odoo_addons/account_voucher_killer/invoice_view.xml
odoo_addons/account_voucher_killer/i18n/account_voucher_killer.pot
odoo_addons/account_voucher_killer/i18n/es.po
odoo_addons/account_voucher_killer/i18n/fr.po
odoo_addons/account_voucher_killer/i18n/pt_BR.po
odoo_addons/account_voucher_killer/i18n/sl.po
odoo_addons/account_voucher_killer/static/description/icon.png
